parsera/__init__.py
parsera/engine/api_extractor.py
parsera/engine/chunks_extractor.py
parsera/engine/model.py
parsera/engine/simple_extractor.py
parsera/engine/structured_extractor.py
parsera/exceptions.py
parsera/main.py
parsera/page.py
parsera/parsera.py
parsera/utils.py
parsera-0.2.6.dist-info/LICENSE
parsera-0.2.6.dist-info/METADATA
parsera-0.2.6.dist-info/WHEEL
parsera-0.2.6.dist-info/RECORD
