Metadata-Version: 2.3
Name: parsera
Version: 0.2.6
Summary: Lightweight library for scraping web-sites with LLMs
License: GPL-2.0-or-later
Author: Mikhail Zanka
Author-email: raznem@gmail.com
Requires-Python: >=3.10,<4.0
Classifier: License :: OSI Approved :: GNU General Public License v2 or later (GPLv2+)
Classifier: Programming Language :: Python :: 3
Classifier: Programming Language :: Python :: 3.10
Classifier: Programming Language :: Python :: 3.11
Classifier: Programming Language :: Python :: 3.12
Classifier: Programming Language :: Python :: 3.13
Requires-Dist: argparse (>=1.4.0,<2.0.0)
Requires-Dist: colorama (>=0.4.6,<0.5.0)
Requires-Dist: langchain (>=0.3.9,<0.4.0)
Requires-Dist: langchain-openai (>=0.2.8,<0.3.0)
Requires-Dist: langchain-text-splitters (>=0.3.2,<0.4.0)
Requires-Dist: markdownify (>=0.13.1,<0.14.0)
Requires-Dist: playwright (>=1.44.0,<2.0.0)
Requires-Dist: playwright-stealth (>=1.0.6,<2.0.0)
Requires-Dist: python-dotenv (>=1.0.1,<2.0.0)
Requires-Dist: tiktoken (>=0.8.0,<0.9.0)
